setup.py
Windows8/__init__.py
Windows8.egg-info/PKG-INFO
Windows8.egg-info/SOURCES.txt
Windows8.egg-info/dependency_links.txt
Windows8.egg-info/top_level.txt